phlower_tensor/__init__.py
phlower_tensor/_array/__init__.py
phlower_tensor/_array/_interface_wrapper.py
phlower_tensor/_array/_phlower_array.py
phlower_tensor/_array/dense/__init__.py
phlower_tensor/_array/dense/_ndarray_wrapper.py
phlower_tensor/_array/sparse/__init__.py
phlower_tensor/_array/sparse/_sparse_array_wrapper.py
phlower_tensor/_base/__init__.py
phlower_tensor/_base/_dimension.py
phlower_tensor/_batch/__init__.py
phlower_tensor/_batch/_batch.py
phlower_tensor/_fields/__init__.py
phlower_tensor/_fields/_simulation_field.py
phlower_tensor/_tensor/__init__.py
phlower_tensor/_tensor/__init__.pyi
phlower_tensor/_tensor/_dimension/__init__.py
phlower_tensor/_tensor/_dimension/__init__.pyi
phlower_tensor/_tensor/_dimension/_dimension_tensor.py
phlower_tensor/_tensor/_phlower_tensor.py
phlower_tensor/_tensor/_tensor_shape.py
phlower_tensor/collections/__init__.py
phlower_tensor/collections/arrays/__init__.py
phlower_tensor/collections/arrays/_arrays_dict.py
phlower_tensor/collections/tensors/__init__.py
phlower_tensor/collections/tensors/_interface.py
phlower_tensor/collections/tensors/_tensor_collections.py
phlower_tensor/functionals/__init__.py
phlower_tensor/functionals/_broadcast_to.py
phlower_tensor/functionals/_check.py
phlower_tensor/functionals/_concatenate.py
phlower_tensor/functionals/_functions.py
phlower_tensor/functionals/_to_batch.py
phlower_tensor/functionals/_to_batch.pyi
phlower_tensor/functionals/_unbatch.py
phlower_tensor/functionals/_unbatch.pyi
phlower_tensor/py.typed
phlower_tensor/utils/__init__.py
phlower_tensor/utils/_logging.py
phlower_tensor/utils/enums.py
phlower_tensor/utils/exceptions.py
phlower_tensor/utils/typing.py
phlower_tensor-0.1.1.dist-info/WHEEL
phlower_tensor-0.1.1.dist-info/METADATA
phlower_tensor-0.1.1.dist-info/RECORD
