Metadata-Version: 2.4
Name: phlower-tensor
Version: 0.1.1
Summary: A PyTorch tensor extension for physical dimension-aware tensors.
Author: RICOS Co. Ltd.
License-Expression: Apache-2.0
Requires-Dist: einops>=0.8.1
Requires-Dist: numpy>=2.3.5
Requires-Dist: pipe>=2.2
Requires-Dist: scipy>=1.16.3
Requires-Dist: torch>=2.5.1 ; extra == 'cpu'
Requires-Dist: torchvision>=0.20.1 ; extra == 'cpu'
Requires-Dist: torch>=2.5.1 ; extra == 'cu118'
Requires-Dist: torchvision>=0.20.1 ; extra == 'cu118'
Requires-Dist: torch>=2.5.1 ; extra == 'cu124'
Requires-Dist: torchvision>=0.20.1 ; extra == 'cu124'
Maintainer: Riku Sakamoto
Maintainer-email: Riku Sakamoto <sakamoto@ricos.co.jp>
Requires-Python: >=3.11
Provides-Extra: cpu
Provides-Extra: cu118
Provides-Extra: cu124
